hack4u/__init__.py
hack4u/courses.py
hack4u/utils.py
hackito4u-0.18.0.dist-info/METADATA
hackito4u-0.18.0.dist-info/WHEEL
hackito4u-0.18.0.dist-info/top_level.txt
hackito4u-0.18.0.dist-info/RECORD
