Metadata-Version: 2.1
Name: hackito4u
Version: 0.18.0
Summary: Una biblioteca para consultar cursos de hack4u
Home-page: https://hack4u.io
Author: Lixus
